README.md
setup.py
example/__init__.py
example/demo.py
screcord/__init__.py
screcord/xrecord
screcord.egg-info/PKG-INFO
screcord.egg-info/SOURCES.txt
screcord.egg-info/dependency_links.txt
screcord.egg-info/requires.txt
screcord.egg-info/top_level.txt