Metadata-Version: 1.2
Name: screcord
Version: 0.0.7
Summary: A python wrapper for Android/iOS screen recording.
Home-page: https://github.com/ssfanli/screcord.git
Author: ssfanli
Author-email: freedomlidi@163.com
License: MIT
Platform: UNKNOWN
Requires-Python: >=3.6
